cnfixedratebond-0.3.0.dist-info/licenses/LICENSE
fixedratebond/__init__.py
cnfixedratebond-0.3.0.dist-info/METADATA
cnfixedratebond-0.3.0.dist-info/WHEEL
cnfixedratebond-0.3.0.dist-info/top_level.txt
cnfixedratebond-0.3.0.dist-info/RECORD
