Metadata-Version: 2.4
Name: cnfixedratebond
Version: 0.3.0
Summary: Fixed rate bond in ib, sse and szse
Author-email: Rho Zhang <rhozhang@163.com>
License-Expression: MIT
Project-URL: Homepage, https://gitee.com/rhozhang/cnfixedratebond
Project-URL: Issues, https://gitee.com/rhozhang/cnfixedratebond/issues
Classifier: Programming Language :: Python :: 3
Classifier: Operating System :: OS Independent
Requires-Python: >=3.12
License-File: LICENSE
Requires-Dist: numpy
Dynamic: license-file
